intuned_browser/__init__.py
intuned_browser/ai/__init__.py
intuned_browser/ai/extract_structured_data.py
intuned_browser/ai/extract_structured_data_using_ai.py
intuned_browser/ai/is_page_loaded.py
intuned_browser/ai/prompts/extract_structured_data_prompt.py
intuned_browser/ai/tests/test_extract_structured_data.py
intuned_browser/ai/tests/test_is_page_loaded.py
intuned_browser/ai/tests/test_matching.py
intuned_browser/ai/tools/extraction_tools.py
intuned_browser/ai/types/__init__.py
intuned_browser/ai/types/content_items.py
intuned_browser/ai/types/data_extraction_errors.py
intuned_browser/ai/types/extract_data_output.py
intuned_browser/ai/types/mathcing_types.py
intuned_browser/ai/types/running_environment.py
intuned_browser/ai/utils/__init__.py
intuned_browser/ai/utils/build_images.py
intuned_browser/ai/utils/collect_strings.py
intuned_browser/ai/utils/convert_string_spaces.py
intuned_browser/ai/utils/create_messages.py
intuned_browser/ai/utils/matching/__init__.py
intuned_browser/ai/utils/matching/matching.py
intuned_browser/ai/utils/safe_json_loads.py
intuned_browser/ai/utils/validate_schema.py
intuned_browser/common/__init__.py
intuned_browser/common/browser_scripts.js
intuned_browser/common/evaluate_with_intuned.py
intuned_browser/common/hash_object.py
intuned_browser/common/tests/test_evaluate_with_intuned.py
intuned_browser/common/types.py
intuned_browser/helpers/__init__.py
intuned_browser/helpers/click_until_exhausted.py
intuned_browser/helpers/download_file.py
intuned_browser/helpers/extract_markdown.py
intuned_browser/helpers/filter_empty_values.py
intuned_browser/helpers/frame_utils/__init__.py
intuned_browser/helpers/frame_utils/check_frame_allows_async_script.py
intuned_browser/helpers/frame_utils/constants.py
intuned_browser/helpers/frame_utils/find_all_iframes.py
intuned_browser/helpers/frame_utils/get_container_frame.py
intuned_browser/helpers/frame_utils/tests/test_find_all_iframes.py
intuned_browser/helpers/go_to_url.py
intuned_browser-0.1.13.dist-info/LICENSE
intuned_browser-0.1.13.dist-info/METADATA
intuned_browser-0.1.13.dist-info/WHEEL
intuned_browser-0.1.13.dist-info/RECORD
