Metadata-Version: 2.3
Name: intuned-browser
Version: 0.1.13
Summary: Intuned Browser SDK
License: Elastic-2.0
Keywords: sdk,intuned
Author: Intuned Developers
Author-email: engineering@intunedhq.com
Requires-Python: >=3.9,<4.0
Classifier: License :: Other/Proprietary License
Classifier: Operating System :: OS Independent
Classifier: Programming Language :: Python :: 3
Classifier: Programming Language :: Python :: 3.9
Classifier: Programming Language :: Python :: 3.10
Classifier: Programming Language :: Python :: 3.11
Classifier: Programming Language :: Python :: 3.12
Classifier: Programming Language :: Python :: 3.13
Requires-Dist: Levenshtein (>=0.26.0,<0.27.0)
Requires-Dist: aioboto3 (>=14.1.0,<15.0.0)
Requires-Dist: aiofiles (>=24.1.0,<25.0.0)
Requires-Dist: beautifulsoup4 (>=4.12.3,<5.0.0)
Requires-Dist: botocore (>=1.34.70,<2.0.0)
Requires-Dist: fuzzysearch (>=0.7.3,<0.8.0)
Requires-Dist: httpx (>=0.27.2)
Requires-Dist: litellm (>=1.67.2,<2.0.0)
Requires-Dist: mdformat (>=0.7.18,<0.8.0)
Requires-Dist: python-dateutil (>=2.9.0,<3.0.0)
Requires-Dist: python-dotenv (>=1.0.1,<2.0.0)
Requires-Dist: ruff (>=0.7.2)
Requires-Dist: termcolor (>=2.5.0,<3.0.0)
Requires-Dist: types-aioboto3[essential] (>=14.1.0,<15.0.0)
Requires-Dist: validators (>=0.34.0,<0.35.0)
